setup.py
rsnd_distributions/Binomialdistribution.py
rsnd_distributions/Gaussiandistribution.py
rsnd_distributions/Generaldistribution.py
rsnd_distributions/__init__.py
rsnd_distributions.egg-info/PKG-INFO
rsnd_distributions.egg-info/SOURCES.txt
rsnd_distributions.egg-info/dependency_links.txt
rsnd_distributions.egg-info/not-zip-safe
rsnd_distributions.egg-info/top_level.txt