Metadata-Version: 1.0
Name: rsnd-distributions
Version: 0.1
Summary: Gaussian distributions
Home-page: UNKNOWN
Author: Roshan Madipalli
Author-email: roshan26102000@gmail.com
License: UNKNOWN
Platform: UNKNOWN
